MANIFEST.in
README.md
setup.cfg
setup.py
kervi.egg-info/PKG-INFO
kervi.egg-info/SOURCES.txt
kervi.egg-info/dependency_links.txt
kervi.egg-info/requires.txt
kervi.egg-info/top_level.txt
kervi/application/__init__.py
kervi/application/default_config.py
kervi/application/kervi_module.py
kervi/io/__init__.py
kervi/messaging/__init__.py
kervi/messaging/message_manager.py
kervi/messaging/sms.py
kervi/messaging/user_log.py
kervi/module/__init__.py
kervi/module/default_config.py
kervi/plugin/kervi_plugin.py
kervi/plugin/plugin_manager.py
kervi/plugin/authentication/authentication_plugin.py
kervi/plugin/authentication/plain/__init__.py
kervi/plugin/io/files/__init__.py
kervi/plugin/ipc/websocket/__init__.py
kervi/plugin/ipc/websocket/socket_spine.py
kervi/plugin/message_bus/bus_manager.py
kervi/plugin/message_bus/kervi_bus.py
kervi/plugin/message_bus/kervi_bus_plugin.py
kervi/plugin/message_bus/zmq/__init__.py
kervi/plugin/message_bus/zmq/named_lists.py
kervi/plugin/message_bus/zmq/zmqbus.py
kervi/plugin/messaging/message_plugin.py
kervi/plugin/messaging/email/__init__.py
kervi/plugin/messaging/user_log/__init__.py
kervi/plugin/routing/routing_plugin.py
kervi/plugin/routing/kervi_io/__init__.py
kervi/plugin/routing/kervi_io/mq_router.py
kervi/plugin/routing/kervi_io/rbmq.py
kervi/plugin/storage/storage_plugin.py
kervi/plugin/storage/sqlite/__init__.py
kervi/plugin/storage/sqlite_temp/__init__.py
kervi/plugin/webserver/__init__.py
kervi/plugin/webserver/build_in/__init__.py
kervi/plugin/webserver/build_in/web_server.py
kervi/routing/router.py
kervi/routing/routing_manager.py
kervi/storage/sqlite.py
kervi/storage/storage_manager.py
kervi/utility/__init__.py
kervi/utility/application_helpers.py
kervi/utility/authorization.py
kervi/utility/authorization_manager.py
kervi/utility/cron.py
kervi/utility/discovery.py
kervi/utility/encryption.py
kervi/utility/logging_handler.py
kervi/utility/nethelper.py
kervi/version/__init__.py
kervi/vision/__init__.py
kervi/vision/_region_observers.py
kervi/vision/camera.py
kervi/vision/region.py
kervi/vision/region_observer.py
kervi/vision/zip_camera_driver.py
