Metadata-Version: 1.2
Name: kervi
Version: 0.21.5
Summary: 
Home-page: https://kervi.org
Author: Tim Wentzlau
Author-email: tim.wentzlau@gmail.com
License: UNKNOWN
Keywords: raspberry pi,robotic,automation
Platform: UNKNOWN
Classifier: License :: OSI Approved :: MIT License
Classifier: Development Status :: 4 - Beta
Classifier: Intended Audience :: Developers
Classifier: Intended Audience :: Education
Classifier: Intended Audience :: Information Technology
Classifier: Intended Audience :: Manufacturing
Classifier: Intended Audience :: Science/Research
Classifier: Topic :: Scientific/Engineering
Classifier: Topic :: Scientific/Engineering :: Human Machine Interfaces
Classifier: Topic :: Software Development :: Documentation
Classifier: Topic :: System :: Monitoring
Classifier: Environment :: Console
Classifier: Operating System :: Microsoft :: Windows
Classifier: Operating System :: MacOS
Classifier: Operating System :: POSIX :: Linux
Classifier: Programming Language :: Python :: 3.5
Requires-Python: >=3.5.0
